punsy/__init__.py
punsy/cmu.py
punsy/data/cmudict-0.7b.utf8
punsy/structs/__init__.py
punsy/structs/suffix_trie.py
punsy/structs/trie.py
test/__init__.py
test/structs/__init__.py
test/structs/test_trie.py
punsy-0.0.4.dist-info/LICENSE
punsy-0.0.4.dist-info/METADATA
punsy-0.0.4.dist-info/WHEEL
punsy-0.0.4.dist-info/entry_points.txt
punsy-0.0.4.dist-info/top_level.txt
punsy-0.0.4.dist-info/RECORD
