Metadata-Version: 2.1
Name: punsy
Version: 0.0.4
Summary: A rhyming pun generator.
Home-page: https://github.com/tmck-code/punsy
Author: Tom McKeesick
Author-email: tmck01@gmail.com
License: UNKNOWN
Platform: UNKNOWN
Classifier: Programming Language :: Python :: 3
